[{"Pressed": "'s'"}, {"Held": "'s'"}, {"Released": "'s'"}, {"Pressed": "'n'"}, {"Held": "'n'"}, {"Released": "'n'"}, {"Pressed": "'a'"}, {"Held": "'a'"}, {"Released": "'a'"}, {"Pressed": "'p'"}, {"Held": "'p'"}, {"Released": "'p'"}, {"Pressed": "Key.space"}, {"Held": "Key.space"}, {"Released": "Key.space"}, {"Pressed": "'c'"}, {"Held": "'c'"}, {"Released": "'c'"}, {"Pressed": "'h'"}, {"Held": "'h'"}, {"Held": "'a'"}, {"Released": "'h'"}, {"Released": "'a'"}, {"Pressed": "'t'"}, {"Held": "'t'"}, {"Released": "'t'"}, {"Pressed": "Key.enter"}, {"Held": "Key.enter"}, {"Released": "Key.enter"}, {"Pressed": "'u'"}, {"Held": "'u'"}, {"Released": "'u'"}, {"Pressed": "'s'"}, {"Held": "'s'"}, {"Released": "'s'"}, {"Pressed": "'e'"}, {"Held": "'e'"}, {"Held": "'r'"}, {"Released": "'e'"}, {"Released": "'r'"}, {"Pressed": "'n'"}, {"Held": "'n'"}, {"Held": "'a'"}, {"Released": "'n'"}, {"Pressed": "'m'"}, {"Held": "'m'"}, {"Released": "'a'"}, {"Released": "'m'"}, {"Pressed": "'e'"}, {"Held": "'e'"}, {"Released": "'e'"}, {"Pressed": "Key.space"}, {"Held": "Key.space"}, {"Released": "Key.space"}, {"Pressed": "Key.enter"}, {"Held": "Key.enter"}, {"Released": "Key.enter"}]